tacv/__init__.py
tacv/cli/__init__.py
tacv/cli/cli.py
tacv/detection/__init__.py
tacv/detection/centernet/CenterNet.py
tacv/detection/centernet/Trainer.py
tacv/detection/centernet/__init__.py
tacv/detection/centernet/backbones/__init__.py
tacv/detection/centernet/backbones/resnet.py
tacv/detection/centernet/heads/__init__.py
tacv/detection/centernet/losses/__init__.py
tacv/detection/centernet/losses/losses.py
tacv/detection/centernet/utils/__init__.py
tacv/detection/centernet/utils/common.py
tacv/detection/centernet/utils/data_utils.py
tacv/detection/centernet/utils/geometry_utils.py
tacv/detection/centernet/utils/infer.py
tacv/detection/centernet/utils/lightning_utils.py
tacv/detection/centernet/utils/pytorch_model_utils.py
tacv/fileUtils/__init__.py
tacv/fileUtils/fileutils.py
tacv/fileUtils/thread_downloader.py
tacv/geometry/__init__.py
tacv/geometry/iou.py
tacv/resources/__init__.py
tacv/torch/__init__.py
tacv/torch/example_lora.py
tacv/torch/lora_any.py
tacv/torch/model_utils.py
tacv/video/__init__.py
tacv/video/video_proc.py
tacv/visual/__init__.py
tacv/visual/draw2d.py
tacv-1.1.8.data/data/requirements.txt
tacv-1.1.8.dist-info/LICENSE
tacv-1.1.8.dist-info/METADATA
tacv-1.1.8.dist-info/WHEEL
tacv-1.1.8.dist-info/entry_points.txt
tacv-1.1.8.dist-info/top_level.txt
tacv-1.1.8.dist-info/RECORD
