Metadata-Version: 2.1
Name: tacv
Version: 1.1.8
Summary: A mini package for daily tasks
Home-page: https://github.com/TaQuangTu/TaCV
Author: QuangTu-Ta
Author-email: taquangtu132@gmail.com
License: LICENSE
Classifier: Programming Language :: Python :: 3
Classifier: License :: OSI Approved :: MIT License
Classifier: Operating System :: OS Independent
License-File: LICENSE
Requires-Dist: numpy
Requires-Dist: opencv-python
Requires-Dist: tqdm
Requires-Dist: shapely
Requires-Dist: loguru
